Workbook

Sheet Resumen
A1: LUCK.IO — Resumen de ejecución de pruebas (Entrega 1)
A2: Modelado, Verificación y Pruebas · Pontificia Universidad Javeriana Cali · Abraham Waggon, Lupi Andrés Mendoza, Juan Miguel Cáceres
A4: Indicador | B4: Caja blanca | C4: Caja negra | D4: Total
A5: Casos diseñados | B5: =COUNTA('Casos caja blanca'!A2:A200) -> 72 | C5: =COUNTA('Casos caja negra'!A2:A400) -> 232 | D5: =B5+C5 -> 304
A6: Ciclo 1 (código original): pasaron | B6: =COUNTIF('Casos caja blanca'!K2:K200,"PASÓ") -> 72 | C6: =COUNTIF('Casos caja negra'!I2:I400,"PASÓ") -> 224 | D6: =B6+C6 -> 296
A7: Ciclo 1: fallaron | B7: =COUNTIF('Casos caja blanca'!K2:K200,"FALLÓ") -> 0 | C7: =COUNTIF('Casos caja negra'!I2:I400,"FALLÓ") -> 8 | D7: =B7+C7 -> 8
A8: Ciclo 1: % de casos exitosos | B8: =B6/B5 -> 1 | C8: =C6/C5 -> 0.96551724 | D8: =D6/D5 -> 0.97368421
A9: Ciclo 2 (código corregido): pasaron | B9: =COUNTIF('Casos caja blanca'!M2:M200,"PASÓ") -> 72 | C9: =COUNTIF('Casos caja negra'!K2:K400,"PASÓ") -> 232 | D9: =B9+C9 -> 304
A10: Ciclo 2: fallaron | B10: =COUNTIF('Casos caja blanca'!M2:M200,"FALLÓ") -> 0 | C10: =COUNTIF('Casos caja negra'!K2:K400,"FALLÓ") -> 0 | D10: =B10+C10 -> 0
A11: Ciclo 2: % de casos exitosos | B11: =B9/B5 -> 1 | C11: =C9/C5 -> 1 | D11: =D9/D5 -> 1
A12: Criterio de salida: ≥ 90% de casos exitosos | B12: =IF(B11>=0.9,"CUMPLE","NO CUMPLE") -> CUMPLE | C12: =IF(C11>=0.9,"CUMPLE","NO CUMPLE") -> CUMPLE | D12: =IF(D11>=0.9,"CUMPLE","NO CUMPLE") -> CUMPLE
A14: Defectos encontrados (Ciclo 1)
A15: Defectos distintos | B15: =COUNTA(Defectos!A2:A6) -> 5
A16: Defectos corregidos | B16: =COUNTIF(Defectos!J2:J6,"CORREGIDO") -> 5
A17: Puntaje de mutación | B17: =Mutación!B34 -> 0.96428571
A18: Cobertura de sentencias (funciones de caja blanca) | B18: ='Cobertura medida'!F8 -> 1
A19: Cobertura de ramas (funciones de caja blanca) | B19: ='Cobertura medida'!I8 -> 1
A21: Hojas: Casos caja blanca · Casos caja negra · Cobertura - casos mínimos · Cobertura medida · Complejidad ciclomática · Defectos · Mutación · Trazabilidad regla-casos
A22: Técnicas de caja negra: EP = partición de equivalencia, VL = valores límite, TD = tabla de decisión, TE = transición de estados, ES = escenarios.

Sheet Casos caja blanca
A1: ID Caso | B1: Función | C1: Archivo | D1: Objetivo | E1: Datos de entrada | F1: Recorrido (camino en el grafo) | G1: Cubre (S=sentencia D=decisión C=condición P=caminos) | H1: Condiciones | I1: Resultado esperado | J1: Obtenido Ciclo 1 (código original) | K1: Estado C1 | L1: Obtenido Ciclo 2 (código corregido) | M1: Estado C2
A2: CB-RNG-01 | B2: weightedPick | C2: src/utils/rng.js | D2: Salida rápida: el ciclo entra y el if se cumple en la 1.ª vuelta | E2: items=[Cereza w50, Jackpot w10], r=20 | F2: Inicio→N1→N2(Sí)→N3(True)→N4→Fin | G2: S, D, P | H2: for=Sí, if=True | I2: 'Cereza' | J2: 'Cereza' | K2: PASÓ | L2: 'Cereza' | M2: PASÓ
A3: CB-RNG-02 | B3: weightedPick | C3: src/utils/rng.js | D3: Resta de peso y gana en la 2.ª vuelta | E3: items=[Cereza w50, Jackpot w10], r=55 | F3: Inicio→N1→N2(Sí)→N3(False)→N5→N2(Sí)→N3(True)→N4→Fin | G3: S, D, P | H3: if=False y luego True | I3: 'Jackpot' | J3: 'Jackpot' | K3: PASÓ | L3: 'Jackpot' | M3: PASÓ
A4: CB-RNG-03 | B4: weightedPick | C4: src/utils/rng.js | D4: Retorno de seguridad (failsafe): el ciclo termina sin ganar | E4: items=[Cereza w50, Jackpot w10], r=100 (valor imposible inyectado) | F4: Inicio→N1→N2(Sí)→N3(F)→N5→N2(Sí)→N3(F)→N5→N2(No)→N6→Fin | G4: S, D, P | H4: for=No | I4: 'Jackpot' | J4: 'Jackpot' | K4: PASÓ | L4: 'Jackpot' | M4: PASÓ
A5: CB-RNG-04 | B5: weightedPick | C5: src/utils/rng.js | D5: Ciclo con 0 iteraciones (lista vacía) va directo al retorno de seguridad | E5: items=[], r=0 | F5: Inicio→N1→N2(No)→N6→Fin | G5: P | H5: for=No desde el inicio | I5: undefined | J5: undefined | K5: PASÓ | L5: undefined | M5: PASÓ
A6: CB-RNG-05 | B6: weightedPick | C6: src/utils/rng.js | D6: Límite superior del primer ítem: r=49 (< 50) todavía gana Cereza | E6: items=[Cereza w50, Jackpot w10], r=49 | F6: Inicio→N1→N2→N3(True)→N4→Fin | G6: D | H6: if: 49<50 = True | I6: 'Cereza' | J6: 'Cereza' | K6: PASÓ | L6: 'Cereza' | M6: PASÓ
A7: CB-RNG-06 | B7: weightedPick | C7: src/utils/rng.js | D7: Límite: r=50 ya NO es del primer ítem (50<50 es falso) y pasa al Jackpot | E7: items=[Cereza w50, Jackpot w10], r=50 | F7: Inicio→N1→N2→N3(False)→N5→N2→N3(True)→N4→Fin | G7: D | H7: if: 50<50 = False; luego 0<10 = True | I7: 'Jackpot' | J7: 'Jackpot' | K7: PASÓ | L7: 'Jackpot' | M7: PASÓ
A8: CB-RNG-07 | B8: weightedPick | C8: src/utils/rng.js | D8: Una sola opción: con el sorteo real siempre devuelve esa opción | E8: items=[Unico w5], sorteo real | F8: Inicio→N1→N2→N3(True)→N4→Fin | G8: S | H8: r=0 siempre | I8: 'Unico' | J8: 'Unico' | K8: PASÓ | L8: 'Unico' | M8: PASÓ
A9: CB-RNG-08 | B9: weightedPick | C9: src/utils/rng.js | D9: Tres opciones: el peso restado debe acumularse bien (r=60 cae en la 2.ª, no en la última). Caso agregado tras la prueba de mutación | E9: items=[A w50, B w30, C w20], r=60 | F9: Inicio→N1→N2→N3(F)→N5→N2→N3(V)→N4→Fin | G9: D, P | H9: if: 60<50=F; 10<30=V | I9: 'B' | J9: 'B' | K9: PASÓ | L9: 'B' | M9: PASÓ
A10: CB-VIP-01 | B10: calculateVipLevel | C10: src/utils/vip.js | D10: Camino VIP: total muy alto | E10: totalWagered = 60000 | F10: Inicio→N1(V)→N2→Fin | G10: S, D, C, P | H10: una sola condición por decisión | I10: 'VIP LUCK.IO' | J10: 'VIP LUCK.IO' | K10: PASÓ | L10: 'VIP LUCK.IO' | M10: PASÓ
A11: CB-VIP-02 | B11: calculateVipLevel | C11: src/utils/vip.js | D11: Límite exacto 50,000 ya es VIP (>=) | E11: totalWagered = 50000 | F11: Inicio→N1(V)→N2→Fin | G11: D | H11: una sola condición por decisión | I11: 'VIP LUCK.IO' | J11: 'VIP LUCK.IO' | K11: PASÓ | L11: 'VIP LUCK.IO' | M11: PASÓ
A12: CB-VIP-03 | B12: calculateVipLevel | C12: src/utils/vip.js | D12: Límite 49,999 todavía es Oro | E12: totalWagered = 49999 | F12: Inicio→N1(F)→N3(V)→N4→Fin | G12: D | H12: una sola condición por decisión | I12: 'Oro' | J12: 'Oro' | K12: PASÓ | L12: 'Oro' | M12: PASÓ
... A73: CB-RL-16 | B73: settleBets (+ matches) | C73: src/services/rouletteService.js | D73: Tipo de apuesta desconocido: matches cae en default y no paga | E73: tipo "xyz" por 100, sale 5 | F73: matches(default) | G73: D | H73: default del switch | I73: { totalWin: 0, pagos: [ [ false, 0, 0, false ] ] } | J73: { totalWin: 0, pagos: [ [ false, 0, 0, false ] ] } | K73: PASÓ | L73: { totalWin: 0, pagos: [ [ false, 0, 0, false ] ] } | M73: PASÓ

Sheet Casos caja negra
A1: ID Caso | B1: Módulo | C1: Técnica (EP/VL/TD/TE/ES) | D1: Regla de negocio / requisito | E1: Objetivo | F1: Datos de entrada | G1: Resultado esperado | H1: Obtenido Ciclo 1 (código original) | I1: Estado C1 | J1: Obtenido Ciclo 2 (código corregido) | K1: Estado C2
A2: CN-BJR-01 | B2: Blackjack (reglas) | C2: TD | D2: Tabla de pagos del Blackjack (el pago incluye la apuesta devuelta) | E2: Blackjack natural paga 3 a 2 | F2: resultado="blackjack", apuesta=100 | G2: 250 | H2: 250 | I2: PASÓ | J2: 250 | K2: PASÓ
A3: CN-BJR-02 | B3: Blackjack (reglas) | C3: TD | D3: Tabla de pagos del Blackjack (el pago incluye la apuesta devuelta) | E3: Ganar paga 1 a 1 | F3: resultado="win", apuesta=100 | G3: 200 | H3: 200 | I3: PASÓ | J3: 200 | K3: PASÓ
A4: CN-BJR-03 | B4: Blackjack (reglas) | C4: TD | D4: Tabla de pagos del Blackjack (el pago incluye la apuesta devuelta) | E4: Empate devuelve la apuesta | F4: resultado="push", apuesta=100 | G4: 100 | H4: 100 | I4: PASÓ | J4: 100 | K4: PASÓ
A5: CN-BJR-04 | B5: Blackjack (reglas) | C5: TD | D5: Tabla de pagos del Blackjack (el pago incluye la apuesta devuelta) | E5: Perder no devuelve nada | F5: resultado="lose", apuesta=100 | G5: 0 | H5: 0 | I5: PASÓ | J5: 0 | K5: PASÓ
A6: CN-BJR-05 | B6: Blackjack (reglas) | C6: TD | D6: Tabla de pagos del Blackjack (el pago incluye la apuesta devuelta) | E6: Rendirse devuelve la mitad | F6: resultado="surrender", apuesta=100 | G6: 50 | H6: 50 | I6: PASÓ | J6: 50 | K6: PASÓ
A7: CN-BJR-06 | B7: Blackjack (reglas) | C7: TD | D7: Tabla de pagos del Blackjack (el pago incluye la apuesta devuelta) | E7: Blackjack con apuesta impar redondea hacia abajo (62.5 → 62) | F7: resultado="blackjack", apuesta=25 | G7: 62 | H7: 62 | I7: PASÓ | J7: 62 | K7: PASÓ
A8: CN-BJR-07 | B8: Blackjack (reglas) | C8: TD | D8: Tabla de pagos del Blackjack (el pago incluye la apuesta devuelta) | E8: Rendirse con apuesta impar redondea hacia abajo (12.5 → 12) | F8: resultado="surrender", apuesta=25 | G8: 12 | H8: 12 | I8: PASÓ | J8: 12 | K8: PASÓ
A9: CN-BJR-08 | B9: Blackjack (reglas) | C9: VL | D9: Gana quien más se acerque a 21 sin pasarse; el que se pasa pierde | E9: Jugador 21 vs crupier 20 → gana | F9: jugador 21, crupier 20 | G9: 'win' | H9: 'win' | I9: PASÓ | J9: 'win' | K9: PASÓ
A10: CN-BJR-09 | B10: Blackjack (reglas) | C10: VL | D10: Gana quien más se acerque a 21 sin pasarse; el que se pasa pierde | E10: Jugador 20 vs crupier 20 → empate | F10: jugador 20, crupier 20 | G10: 'push' | H10: 'push' | I10: PASÓ | J10: 'push' | K10: PASÓ
A11: CN-BJR-10 | B11: Blackjack (reglas) | C11: VL | D11: Gana quien más se acerque a 21 sin pasarse; el que se pasa pierde | E11: Jugador 20 vs crupier 21 → pierde | F11: jugador 20, crupier 21 | G11: 'lose' | H11: 'lose' | I11: PASÓ | J11: 'lose' | K11: PASÓ
A12: CN-BJR-11 | B12: Blackjack (reglas) | C12: VL | D12: Gana quien más se acerque a 21 sin pasarse; el que se pasa pierde | E12: Crupier se pasó (26) → gana el jugador | F12: jugador 12, crupier 26 | G12: 'win' | H12: 'win' | I12: PASÓ | J12: 'win' | K12: PASÓ
... A233: CN-GEN-06 | B233: API general | C233: VL | D233: RN: máximo 600 peticiones por IP cada 15 minutos | E233: La petición 600 pasa y la 601 es bloqueada con 429 | F233: 601 llamadas seguidas a GET /api/health | G233: { primeras600: 200, la601: 429 } | H233: { primeras600: 200, la601: 429 } | I233: PASÓ | J233: { primeras600: 200, la601: 429 } | K233: PASÓ

Sheet Cobertura - casos mínimos
A1: Función | B1: Archivo | C1: V(G) | D1: Criterio de cobertura | E1: Qué se debe cubrir | F1: Mínimo teórico de casos | G1: Casos que lo cubren | H1: Casos usados | I1: Nota
A2: weightedPick | B2: src/utils/rng.js | C2: 3 | D2: Sentencia | E2: Ejecutar N1…N6 | F2: 3 | G2: CB-RNG-01, CB-RNG-02, CB-RNG-03 | H2: =LEN(G2)-LEN(SUBSTITUTE(G2,",",""))+1 -> 3 | I2: N4 (gana), N5 (resta) y N6 (failsafe) exigen 3 casos distintos
A3: weightedPick | B3: src/utils/rng.js | C3: 3 | D3: Decisión | E3: for: Sí/No · if: True/False | F3: 3 | G3: CB-RNG-01, CB-RNG-02, CB-RNG-03 | H3: =LEN(G3)-LEN(SUBSTITUTE(G3,",",""))+1 -> 3 | I3: for=No solo ocurre agotando la lista (r=100)
A4: weightedPick | B4: src/utils/rng.js | C4: 3 | D4: Condición simple | E4: Cada condición V y F (son las mismas de las decisiones) | F4: 3 | G4: CB-RNG-01, CB-RNG-02, CB-RNG-03 | H4: =LEN(G4)-LEN(SUBSTITUTE(G4,",",""))+1 -> 3 | I4: No hay condiciones compuestas
A5: weightedPick | B5: src/utils/rng.js | C5: 3 | D5: Condición múltiple | E5: No aplica (no hay && ni ||) | F5: 0 | H5: =LEN(G5)-LEN(SUBSTITUTE(G5,",",""))+1 -> 1 | I5: Equivale a decisión
A6: weightedPick | B6: src/utils/rng.js | C6: 3 | D6: Caminos | E6: V(G)=3 caminos independientes + ciclo con 0 iteraciones | F6: 3 | G6: CB-RNG-01, CB-RNG-02, CB-RNG-03, CB-RNG-04 | H6: =LEN(G6)-LEN(SUBSTITUTE(G6,",",""))+1 -> 4 | I6: Se agrega CB-RNG-04 por la prueba de ciclo con 0 iteraciones
A7: calculateVipLevel | B7: src/utils/vip.js | C7: 4 | D7: Sentencia | E7: Ejecutar los 4 return | F7: 4 | G7: CB-VIP-01, CB-VIP-04, CB-VIP-07, CB-VIP-10 | H7: =LEN(G7)-LEN(SUBSTITUTE(G7,",",""))+1 -> 4 | I7: Uno por nivel
A8: calculateVipLevel | B8: src/utils/vip.js | C8: 4 | D8: Decisión | E8: 3 decisiones × (V, F) | F8: 4 | G8: CB-VIP-01, CB-VIP-04, CB-VIP-07, CB-VIP-10 | H8: =LEN(G8)-LEN(SUBSTITUTE(G8,",",""))+1 -> 4 | I8: Los 4 caminos cubren las 6 salidas
A9: calculateVipLevel | B9: src/utils/vip.js | C9: 4 | D9: Condición simple | E9: Igual que decisión (1 condición por if) | F9: 4 | G9: CB-VIP-01, CB-VIP-04, CB-VIP-07, CB-VIP-10 | H9: =LEN(G9)-LEN(SUBSTITUTE(G9,",",""))+1 -> 4
A10: calculateVipLevel | B10: src/utils/vip.js | C10: 4 | D10: Condición múltiple | E10: No aplica | F10: 0 | H10: =LEN(G10)-LEN(SUBSTITUTE(G10,",",""))+1 -> 1
A11: calculateVipLevel | B11: src/utils/vip.js | C11: 4 | D11: Caminos | E11: V(G)=4 caminos independientes | F11: 4 | G11: CB-VIP-01, CB-VIP-04, CB-VIP-07, CB-VIP-10 | H11: =LEN(G11)-LEN(SUBSTITUTE(G11,",",""))+1 -> 4 | I11: Se agregan 6 casos de valor límite (50000/49999, 20000/19999, 5000/4999) para detectar > en vez de >=
A12: handScore (+ cardValue) | B12: src/services/blackjackRules.js | C12: 5 | D12: Sentencia | E12: Ejecutar N1…N9 | F12: 1 | G12: CB-HS-04 | H12: =LEN(G12)-LEN(SUBSTITUTE(G12,",",""))+1 -> 1 | I12: Una mano con As que se pasa recorre todas las sentencias
A13: handScore (+ cardValue) | B13: src/services/blackjackRules.js | C13: 5 | D13: Decisión | E13: for, if, while: V y F | F13: 2 | G13: CB-HS-04, CB-HS-02 | H13: =LEN(G13)-LEN(SUBSTITUTE(G13,",",""))+1 -> 2 | I13: if=F lo da cualquier carta no As (la 6 o la 9 en CB-HS-04)
A14: handScore (+ cardValue) | B14: src/services/blackjackRules.js | C14: 5 | D14: Condición simple | E14: A (total>21) y B (aces>0) cada una V y F | F14: 2 | G14: CB-HS-04, CB-HS-05 | H14: =LEN(G14)-LEN(SUBSTITUTE(G14,",",""))+1 -> 2 | I14: B=F con A=V solo ocurre sin Ases y pasándose
A15: handScore (+ cardValue) | B15: src/services/blackjackRules.js | C15: 5 | D15: Condición múltiple | E15: A&&B: VV, VF, FV, FF | F15: 4 | G15: CB-HS-04, CB-HS-05, CB-HS-03, CB-HS-02 | H15: =LEN(G15)-LEN(SUBSTITUTE(G15,",",""))+1 -> 4 | I15: Con cortocircuito la evaluación real tiene 3 salidas (VV, VF, F-)
A16: handScore (+ cardValue) | B16: src/services/blackjackRules.js | C16: 5 | D16: Caminos | E16: V(G)=5 independientes + ciclo while 0/1/2/n | F16: 5 | G16: CB-HS-01, CB-HS-02, CB-HS-03, CB-HS-04, CB-HS-05 | H16: =LEN(G16)-LEN(SUBSTITUTE(G16,",",""))+1 -> 5 | I16: Más CB-HS-06/07/11 para ciclo con 1, 2 y 4 vueltas
A17: canSplit | B17: src/services/blackjackRules.js | C17: 5 | D17: Sentencia | E17: Ejecutar la expresión (1 sentencia) | F17: 1 | G17: CB-SP-06 | H17: =LEN(G17)-LEN(SUBSTITUTE(G17,",",""))+1 -> 1
A18: canSplit | B18: src/services/blackjackRules.js | C18: 5 | D18: Decisión | E18: Resultado true y false | F18: 2 | G18: CB-SP-06, CB-SP-01 | H18: =LEN(G18)-LEN(SUBSTITUTE(G18,",",""))+1 -> 2
A19: canSplit | B19: src/services/blackjackRules.js | C19: 5 | D19: Condición simple | E19: C1…C5 cada una V y F | F19: 6 | G19: CB-SP-06, CB-SP-01, CB-SP-02, CB-SP-03, CB-SP-04, CB-SP-05 | H19: =LEN(G19)-LEN(SUBSTITUTE(G19,",",""))+1 -> 6 | I19: Una verdadera para todas + una falsa por condición
A20: canSplit | B20: src/services/blackjackRules.js | C20: 5 | D20: Condición múltiple | E20: Combinaciones alcanzables con cortocircuito (2⁵=32 teóricas) | F20: 6 | G20: CB-SP-06, CB-SP-01, CB-SP-02, CB-SP-03, CB-SP-04, CB-SP-05 | H20: =LEN(G20)-LEN(SUBSTITUTE(G20,",",""))+1 -> 6 | I20: Con && solo 6 combinaciones son distinguibles (equivale a MC/DC: n+1)
A21: canSplit | B21: src/services/blackjackRules.js | C21: 5 | D21: Caminos | E21: V(G)=5 caminos independientes | F21: 5 | G21: CB-SP-06, CB-SP-01, CB-SP-02, CB-SP-03, CB-SP-04 | H21: =LEN(G21)-LEN(SUBSTITUTE(G21,",",""))+1 -> 5 | I21: CB-SP-05 (C5 falsa) recorre el mismo camino del grafo que CB-SP-06 pero con otro valor; CB-SP-07/08/09 son valores equivalentes y límites
A22: bankerDraws | B22: src/services/baccaratRules.js | C22: 12 | D22: Sentencia | E22: Ejecutar cada return | F22: 7 | G22: CB-BD-01, CB-BD-03, CB-BD-06, CB-BD-09, CB-BD-13, CB-BD-15, CB-BD-18 | H22: =LEN(G22)-LEN(SUBSTITUTE(G22,",",""))+1 -> 7 | I22: Un return por case + default + el de "Punto se plantó"
A23: bankerDraws | B23: src/services/baccaratRules.js | C23: 12 | D23: Decisión | E23: if y cada case V/F (total 0..7) | F23: 12 | G23: CB-BD-01, CB-BD-03, CB-BD-04, CB-BD-05, CB-BD-06, CB-BD-08, CB-BD-09, CB-BD-12, CB-BD-13, CB-BD-15, CB-BD-16, CB-BD-18 | H23: =LEN(G23)-LEN(SUBSTITUTE(G23,",",""))+1 -> 12
A24: bankerDraws | B24: src/services/baccaratRules.js | C24: 12 | D24: Condición simple | E24: p>=2, p<=7, p>=4, p<=7, p===6, p===7 cada una V y F | F24: 9 | G24: CB-BD-08, CB-BD-09, CB-BD-10, CB-BD-12, CB-BD-13, CB-BD-14, CB-BD-15, CB-BD-16, CB-BD-17 | H24: =LEN(G24)-LEN(SUBSTITUTE(G24,",",""))+1 -> 9
A25: bankerDraws | B25: src/services/baccaratRules.js | C25: 12 | D25: Condición múltiple | E25: Combinaciones de cada && / || | F25: 9 | G25: CB-BD-08, CB-BD-09, CB-BD-10, CB-BD-12, CB-BD-13, CB-BD-14, CB-BD-15, CB-BD-16, CB-BD-17 | H25: =LEN(G25)-LEN(SUBSTITUTE(G25,",",""))+1 -> 9 | I25: p>=2&&p<=7 y p>=4&&p<=7: VV,VF,FV(no alcanzable con p entero real en FF); p===6||p===7: V-,FV,FF
A26: bankerDraws | B26: src/services/baccaratRules.js | C26: 12 | D26: Caminos | E26: V(G)=12 | F26: 12 | G26: CB-BD-01, CB-BD-03, CB-BD-04, CB-BD-05, CB-BD-06, CB-BD-08, CB-BD-09, CB-BD-12, CB-BD-13, CB-BD-15, CB-BD-16, CB-BD-18 | H26: =LEN(G26)-LEN(SUBSTITUTE(G26,",",""))+1 -> 12 | I26: Se ejecutan 18 casos
A27: settleBets (+ matches) | B27: src/services/rouletteService.js | C27: 6 | D27: Sentencia | E27: Ejecutar todas las sentencias del callback | F27: 3 | G27: CB-RL-03, CB-RL-05, CB-RL-02 | H27: =LEN(G27)-LEN(SUBSTITUTE(G27,",",""))+1 -> 3 | I27: bono caliente, La Partage y pago normal
A28: settleBets (+ matches) | B28: src/services/rouletteService.js | C28: 6 | D28: Decisión | E28: won, ternario, else-if: V y F | F28: 4 | G28: CB-RL-02, CB-RL-03, CB-RL-05, CB-RL-06 | H28: =LEN(G28)-LEN(SUBSTITUTE(G28,",",""))+1 -> 4
A29: settleBets (+ matches) | B29: src/services/rouletteService.js | C29: 6 | D29: Condición simple | E29: A, B, C, D cada una V y F | F29: 5 | G29: CB-RL-02, CB-RL-03, CB-RL-04, CB-RL-05, CB-RL-07, CB-RL-06 | H29: =LEN(G29)-LEN(SUBSTITUTE(G29,",",""))+1 -> 6 | I29: B=F con lista no vacía en CB-RL-04
A30: settleBets (+ matches) | B30: src/services/rouletteService.js | C30: 6 | D30: Condición múltiple | E30: A&&B y C&&D | F30: 6 | G30: CB-RL-02, CB-RL-03, CB-RL-11, CB-RL-05, CB-RL-07, CB-RL-06 | H30: =LEN(G30)-LEN(SUBSTITUTE(G30,",",""))+1 -> 6 | I30: A&&B: VV, VF, F-; C&&D: VV, VF, F-
A31: settleBets (+ matches) | B31: src/services/rouletteService.js | C31: 6 | D31: Caminos | E31: V(G)=6 + ciclo map con 0/1/n | F31: 6 | G31: CB-RL-01, CB-RL-02, CB-RL-03, CB-RL-05, CB-RL-06, CB-RL-07 | H31: =LEN(G31)-LEN(SUBSTITUTE(G31,",",""))+1 -> 6 | I31: CB-RL-13 recorre el map con 3 iteraciones

Sheet Cobertura medida
A1: Función | B1: Archivo | C1: Líneas | D1: Sentencias totales | E1: Sentencias cubiertas | F1: % sentencias | G1: Ramas totales | H1: Ramas cubiertas | I1: % ramas
A2: weightedPick | B2: src/utils/rng.js | C2: 5-13 | D2: 9 | E2: 9 | F2: =E2/D2 -> 1 | G2: 6 | H2: 6 | I2: =H2/G2 -> 1
A3: calculateVipLevel | B3: src/utils/vip.js | C3: 1-6 | D3: 6 | E3: 6 | F3: =E3/D3 -> 1 | G3: 8 | H3: 8 | I3: =H3/G3 -> 1
A4: handScore (+ cardValue) | B4: src/services/blackjackRules.js | C4: 3-7, 10-22 | D4: 18 | E4: 18 | F4: =E4/D4 -> 1 | G4: 10 | H4: 10 | I4: =H4/G4 -> 1
A5: canSplit | B5: src/services/blackjackRules.js | C5: 58-63 | D5: 6 | E5: 6 | F5: =E5/D5 -> 1 | G5: 5 | H5: 5 | I5: =H5/G5 -> 1
A6: bankerDraws (+ points) | B6: src/services/baccaratRules.js | C6: 6-10, 18-31 | D6: 19 | E6: 19 | F6: =E6/D6 -> 1 | G6: 19 | H6: 19 | I6: =H6/G6 -> 1
A7: settleBets (+ matches) | B7: src/services/rouletteService.js | C7: 15-32, 55-75 | D7: 39 | E7: 39 | F7: =E7/D7 -> 1 | G7: 26 | H7: 26 | I7: =H7/G7 -> 1
A8: TOTAL | D8: =SUM(D2:D7) -> 97 | E8: =SUM(E2:E7) -> 97 | F8: =E8/D8 -> 1 | G8: =SUM(G2:G7) -> 74 | H8: =SUM(H2:H7) -> 74 | I8: =H8/G8 -> 1
A10: Fuente: node --test --experimental-test-coverage (V8) filtrado por las líneas de cada función. Evidencia: evidencias/cobertura/

Sheet Complejidad ciclomática
A1: Función | B1: Nodos (N) | C1: Aristas (E) | D1: V(G) = E − N + 2 | E1: V(G) medido con ESLint (regla complexity) | F1: ¿Coincide?
A2: weightedPick | B2: 8 | C2: 9 | D2: =C2-B2+2 -> 3 | E2: 3 | F2: =IF(D2=E2,"Sí","NO") -> Sí
A3: calculateVipLevel | B3: 9 | C3: 11 | D3: =C3-B3+2 -> 4 | E3: 4 | F3: =IF(D3=E3,"Sí","NO") -> Sí
A4: handScore (+ cardValue) | B4: 11 | C4: 14 | D4: =C4-B4+2 -> 5 | E4: 5 | F4: =IF(D4=E4,"Sí","NO") -> Sí
A5: canSplit | B5: 8 | C5: 11 | D5: =C5-B5+2 -> 5 | E5: 5 | F5: =IF(D5=E5,"Sí","NO") -> Sí
A6: bankerDraws | B6: 22 | C6: 32 | D6: =C6-B6+2 -> 12 | E6: 12 | F6: =IF(D6=E6,"Sí","NO") -> Sí
A7: settleBets (+ matches) | B7: 15 | C7: 19 | D7: =C7-B7+2 -> 6 | E7: 6 | F7: =IF(D7=E7,"Sí","NO") -> Sí

Sheet Defectos
A1: ID | B1: Severidad | C1: Módulo | D1: Descripción del defecto | E1: Casos que lo detectaron | F1: Técnica | G1: Resultado obtenido (Ciclo 1) | H1: Resultado esperado | I1: Corrección aplicada | J1: Estado
A2: DEF-01 | B2: Alta | C2: Ruleta | D2: Una selección vacía o nula (null, "", [], false) en un pleno se interpreta como el número 0: la apuesta se acepta y puede pagar 35:1 sin que el jugador eligiera número. | E2: CN-RL-14, CN-RLR-05 | F2: TD / EP | G2: Respuesta 200 y saldo cambia en las 4 entradas | H2: Debe rechazar con 400 y no tocar el saldo | I2: Se agregó parseIntSelection (src/services/rouletteService.js) y se usa en rouletteRoutes.js y normalizeBet | J2: CORREGIDO
A3: DEF-02 | B3: Media | C3: Cuentas | D3: Login con contraseña que no es texto (objeto, número, lista) provoca error 500 del servidor en lugar de 400. | E3: CN-AUTH-28 | F3: EP | G3: Estados [500, 500, 500] | H3: Estados [400, 400, 400] | I3: isString().bail() en las validaciones de authRoutes.js (registro y login) y manejo de CastError/ValidationError en middleware/error.js | J3: CORREGIDO
A4: DEF-03 | B4: Baja | C4: Blackjack | D4: El seguro acepta take=1 y take="1" como verdadero (solo debería aceptar true/false). | E4: CN-BJ-32 | F4: EP / VL | G4: Estados [200, 200, 400] | H4: Estados [400, 400, 400] | I4: Validador isIn(['true','false']) en blackjackRoutes.js | J4: CORREGIDO
A5: DEF-04 | B5: Media | C5: Blackjack | D5: Un identificador de partida mal formado ("abc") en la URL produce error 500 (CastError de Mongoose) en lugar de 400. | E5: CN-BJ-42 | F5: EP | G5: Estado 500 | H5: Estado 400 "Identificador de partida inválido" | I5: router.param('id') valida 24 caracteres hexadecimales; error.js traduce CastError a 400 | J5: CORREGIDO
A6: DEF-05 | B6: Crítica | C6: Blackjack | D6: Condición de carrera: dos peticiones simultáneas del mismo jugador se ejecutan a la vez. Se cobran dos apuestas y se crean dos partidas (start), se cobra dos veces el doblado (double) y dos veces el seguro (insurance). | E6: CN-BJ-43, CN-BJ-44, CN-BJ-45 | F6: ES (escenario concurrente) | G6: 2 partidas, 2 apuestas, saldo 9800; 2 cobros de doblado; 2 cobros de seguro | H6: 1 partida, 1 apuesta, saldo 9900; 1 cobro; 1 cobro | I6: Se creó utils/mutex.js (exclusivo) y blackjackController.js serializa cada acción por jugador. Limitación: solo protege una instancia del servidor | J6: CORREGIDO

Sheet Mutación
A1: ID mutante | B1: Función | C1: Archivo | D1: Cambio introducido a propósito | E1: Ronda 1 (antes de agregar CB-RNG-08): estado y quién lo detectó | F1: Ronda final | G1: Detectado por
A2: M01 | B2: weightedPick | C2: src/utils/rng.js | D2: Cambiar < por <= en la comparación del peso | E2: MUERTO (caja blanca) | F2: MUERTO | G2: caja blanca
A3: M02 | B3: weightedPick | C3: src/utils/rng.js | D3: Sumar en vez de restar el peso | E3: MUERTO (caja negra) | F3: MUERTO | G3: caja blanca
A4: M03 | B4: weightedPick | C4: src/utils/rng.js | D4: Retorno de seguridad devuelve el primer ítem | E4: MUERTO (caja blanca) | F4: MUERTO | G4: caja blanca
A5: M04 | B5: calculateVipLevel | C5: src/utils/vip.js | D5: Límite de VIP: >= pasa a > | E5: MUERTO (caja blanca) | F5: MUERTO | G5: caja blanca
A6: M05 | B6: calculateVipLevel | C6: src/utils/vip.js | D6: Límite de Oro: >= pasa a > | E6: MUERTO (caja blanca) | F6: MUERTO | G6: caja blanca
A7: M06 | B7: calculateVipLevel | C7: src/utils/vip.js | D7: Límite de Plata: >= pasa a > | E7: MUERTO (caja blanca) | F7: MUERTO | G7: caja blanca
A8: M07 | B8: calculateVipLevel | C8: src/utils/vip.js | D8: Nivel Oro devuelve Plata | E8: MUERTO (caja blanca) | F8: MUERTO | G8: caja blanca
A9: M08 | B9: handScore | C9: src/services/blackjackRules.js | D9: Ajustar el As también cuando la mano vale exactamente 21 | E9: MUERTO (caja blanca) | F9: MUERTO | G9: caja blanca
A10: M09 | B10: handScore | C10: src/services/blackjackRules.js | D10: El último As ya no baja a 1 | E10: MUERTO (caja blanca) | F10: MUERTO | G10: caja blanca
A11: M10 | B11: handScore | C11: src/services/blackjackRules.js | D11: Al bajar un As se resta 9 en vez de 10 | E11: MUERTO (caja blanca) | F11: MUERTO | G11: caja blanca
A12: M11 | B12: handScore | C12: src/services/blackjackRules.js | D12: No se cuentan los Ases | E12: MUERTO (caja blanca) | F12: MUERTO | G12: caja blanca
... A29: M28 | B29: matches | C29: src/services/rouletteService.js | D29: Pleno paga 35× total (el error real que se corrigió antes) | E29: MUERTO (caja blanca) | F29: MUERTO | G29: caja blanca
A31: Total mutantes | B31: =COUNTA(A2:A29) -> 28
A32: Detectados (MUERTO) | B32: =COUNTIF(F2:F29,"MUERTO") -> 27
A33: Sobrevivieron | B33: =B31-B32 -> 1
A34: Puntaje de mutación | B34: =B32/B31 -> 0.96428571
A36: M15 es un mutante equivalente a propósito (!x vs x!==true cuando x es booleano): debe sobrevivir. M02 no fue detectado por la caja blanca en la ronda 1 (solo lo mató la caja negra), por eso se agregó el caso CB-RNG-08.

Sheet Trazabilidad regla-casos
A1: Módulo | B1: Regla de negocio | C1: Casos que la verifican | D1: N.º de casos
A2: API general | B2: RN: el cuerpo de una petición no puede pasar de 10 KB | C2: CN-GEN-03 | D2: =LEN(C2)-LEN(SUBSTITUTE(C2,",",""))+1 -> 1
A3: API general | B3: RN: la API no revela la tecnología del servidor | C3: CN-GEN-05 | D3: =LEN(C3)-LEN(SUBSTITUTE(C3,",",""))+1 -> 1
A4: API general | B4: RN: máximo 600 peticiones por IP cada 15 minutos | C4: CN-GEN-06 | D4: =LEN(C4)-LEN(SUBSTITUTE(C4,",",""))+1 -> 1
A5: API general | B5: RN: rutas desconocidas responden JSON 404 | C5: CN-GEN-01 | D5: =LEN(C5)-LEN(SUBSTITUTE(C5,",",""))+1 -> 1
A6: API general | B6: RN: solo el frontend autorizado puede llamar a la API desde un navegador (CORS) | C6: CN-GEN-04 | D6: =LEN(C6)-LEN(SUBSTITUTE(C6,",",""))+1 -> 1
A7: API general | B7: RN: un JSON mal formado no tumba el servidor | C7: CN-GEN-02 | D7: =LEN(C7)-LEN(SUBSTITUTE(C7,",",""))+1 -> 1
A8: Bacará | B8: Pago: Banca 1 a 1 con 5% de comisión | C8: CN-BAC-09 | D8: =LEN(C8)-LEN(SUBSTITUTE(C8,",",""))+1 -> 1
A9: Bacará | B9: Pago: Empate 8 a 1; Punto y Banca se devuelven | C9: CN-BAC-10 | D9: =LEN(C9)-LEN(SUBSTITUTE(C9,",",""))+1 -> 1
A10: Bacará | B10: Pago: Par de la Banca 11 a 1 | C10: CN-BAC-14 | D10: =LEN(C10)-LEN(SUBSTITUTE(C10,",",""))+1 -> 1
A11: Bacará | B11: Pago: Par del Punto 11 a 1 (las 2 primeras cartas del mismo valor) | C11: CN-BAC-12 | D11: =LEN(C11)-LEN(SUBSTITUTE(C11,",",""))+1 -> 1
A12: Bacará | B12: Pago: Punto 1 a 1 | C12: CN-BAC-08 | D12: =LEN(C12)-LEN(SUBSTITUTE(C12,",",""))+1 -> 1
A13: Bacará | B13: Pago: apuesta al Empate pierde si no hay empate | C13: CN-BAC-11 | D13: =LEN(C13)-LEN(SUBSTITUTE(C13,",",""))+1 -> 1
... A188: Tragamonedas | B188: Tabla: saldo vs apuesta → saldo menor rechaza sin tocar nada | C188: CN-SLT-06 | D188: =LEN(C188)-LEN(SUBSTITUTE(C188,",",""))+1 -> 1
